{"":1584,"a":1,"about":2,"activity":1,"all":12,"an":2,"another":2,"api":4,"as":4,"at":1,"back":2,"blog":2,"build":2,"by":2,"classes":2,"clone":4,"clonesnetflixclone":3,"collins":2,"collo":4,"collofollow":1,"collowebscraperjavascript":2,"commit":3,"common":2,"contact":2,"content":1,"contribution":1,"contributions":2,"count":1,"created":1,"data":2,"datastructures":3,"design":2,"devcollinske":2,"docs":2,"ecommerce":1,"end":2,"follow":10,"followers":1,"following":1,"footer":2,"for":4,"frontend":1,"github":17,"guide":2,"halloween":1,"happy":1,"how":1,"httpscollinsoduorvercelapp":2,"implementation":2,"in":15,"inc":1,"instructed":2,"is":4,"javascript":26,"jump":10,"last":1,"learn":1,"look":1,"more":2,"my":4,"nairobi":2,"navigation":2,"netflix":1,"no":2,"october":2,"oduor":1,"oduorcollo":1,"of":2,"or":2,"out":1,"overview":4,"packages":3,"personal":2,"personalportfoliobackend":3,"personalportfoliofrontend":3,"pinned":1,"portfolio":4,"pricing":2,"privacy":2,"profile":2,"projects":4,"public":6,"publicecommerce":1,"publicfrontend":1,"publicnetflix":1,"publictesla":1,"publicthis":2,"refresh":2,"reload":4,"repositories":4,"repository":1,"results":2,"sangha":2,"search":3,"security":2,"seeing":1,"session":2,"shopnjenga":3,"shopping":2,"sign":1,"signed":2,"signup":1,"skip":1,"something":1,"sony":2,"stars":3,"status":2,"structures":2,"suggested":2,"tab":2,"take":1,"terms":2,"tesla":1,"teslacloneuireactnative":3,"the":4,"this":11,"to":13,"toggle":1,"training":2,"unexpected":1,"up":1,"user":9,"we":1,"website":6,"window":2,"with":1,"year":1,"you":2,"your":2}